{"nodes": [{"id": "webhooks", "label": "webhooks.py", "file_type": "code", "source_file": "/mnt/workflows/workflows/apps/backend/app/api/v1/webhooks.py", "source_location": "L1"}, {"id": "webhooks_list_subscriptions", "label": "list_subscriptions()", "file_type": "code", "source_file": "/mnt/workflows/workflows/apps/backend/app/api/v1/webhooks.py", "source_location": "L8"}, {"id": "webhooks_create_subscription", "label": "create_subscription()", "file_type": "code", "source_file": "/mnt/workflows/workflows/apps/backend/app/api/v1/webhooks.py", "source_location": "L13"}, {"id": "webhooks_get_subscription", "label": "get_subscription()", "file_type": "code", "source_file": "/mnt/workflows/workflows/apps/backend/app/api/v1/webhooks.py", "source_location": "L31"}, {"id": "webhooks_delete_subscription", "label": "delete_subscription()", "file_type": "code", "source_file": "/mnt/workflows/workflows/apps/backend/app/api/v1/webhooks.py", "source_location": "L51"}, {"id": "webhooks_list_deliveries", "label": "list_deliveries()", "file_type": "code", "source_file": "/mnt/workflows/workflows/apps/backend/app/api/v1/webhooks.py", "source_location": "L58"}, {"id": "webhooks_get_delivery", "label": "get_delivery()", "file_type": "code", "source_file": "/mnt/workflows/workflows/apps/backend/app/api/v1/webhooks.py", "source_location": "L66"}, {"id": "webhooks_emit_event", "label": "emit_event()", "file_type": "code", "source_file": "/mnt/workflows/workflows/apps/backend/app/api/v1/webhooks.py", "source_location": "L86"}, {"id": "webhooks_get_event_types", "label": "get_event_types()", "file_type": "code", "source_file": "/mnt/workflows/workflows/apps/backend/app/api/v1/webhooks.py", "source_location": "L91"}, {"id": "webhooks_get_stats", "label": "get_stats()", "file_type": "code", "source_file": "/mnt/workflows/workflows/apps/backend/app/api/v1/webhooks.py", "source_location": "L105"}], "edges": [{"source": "webhooks", "target": "fastapi", "relation": "imports_from", "confidence": "EXTRACTED", "source_file": "/mnt/workflows/workflows/apps/backend/app/api/v1/webhooks.py", "source_location": "L1", "weight": 1.0}, {"source": "webhooks", "target": "webhooks_list_subscriptions", "relation": "contains", "confidence": "EXTRACTED", "source_file": "/mnt/workflows/workflows/apps/backend/app/api/v1/webhooks.py", "source_location": "L8", "weight": 1.0}, {"source": "webhooks", "target": "webhooks_create_subscription", "relation": "contains", "confidence": "EXTRACTED", "source_file": "/mnt/workflows/workflows/apps/backend/app/api/v1/webhooks.py", "source_location": "L13", "weight": 1.0}, {"source": "webhooks", "target": "webhooks_get_subscription", "relation": "contains", "confidence": "EXTRACTED", "source_file": "/mnt/workflows/workflows/apps/backend/app/api/v1/webhooks.py", "source_location": "L31", "weight": 1.0}, {"source": "webhooks", "target": "webhooks_delete_subscription", "relation": "contains", "confidence": "EXTRACTED", "source_file": "/mnt/workflows/workflows/apps/backend/app/api/v1/webhooks.py", "source_location": "L51", "weight": 1.0}, {"source": "webhooks", "target": "webhooks_list_deliveries", "relation": "contains", "confidence": "EXTRACTED", "source_file": "/mnt/workflows/workflows/apps/backend/app/api/v1/webhooks.py", "source_location": "L58", "weight": 1.0}, {"source": "webhooks", "target": "webhooks_get_delivery", "relation": "contains", "confidence": "EXTRACTED", "source_file": "/mnt/workflows/workflows/apps/backend/app/api/v1/webhooks.py", "source_location": "L66", "weight": 1.0}, {"source": "webhooks", "target": "webhooks_emit_event", "relation": "contains", "confidence": "EXTRACTED", "source_file": "/mnt/workflows/workflows/apps/backend/app/api/v1/webhooks.py", "source_location": "L86", "weight": 1.0}, {"source": "webhooks", "target": "webhooks_get_event_types", "relation": "contains", "confidence": "EXTRACTED", "source_file": "/mnt/workflows/workflows/apps/backend/app/api/v1/webhooks.py", "source_location": "L91", "weight": 1.0}, {"source": "webhooks", "target": "webhooks_get_stats", "relation": "contains", "confidence": "EXTRACTED", "source_file": "/mnt/workflows/workflows/apps/backend/app/api/v1/webhooks.py", "source_location": "L105", "weight": 1.0}]}