{"nodes": [{"id": "memory_tools", "label": "memory_tools.py", "file_type": "code", "source_file": "/mnt/workflows/workflows/apps/backend/app/tools/memory_tools.py", "source_location": "L1"}, {"id": "memory_tools_storememoryinput", "label": "StoreMemoryInput", "file_type": "code", "source_file": "/mnt/workflows/workflows/apps/backend/app/tools/memory_tools.py", "source_location": "L15"}, {"id": "toolinput", "label": "ToolInput", "file_type": "code", "source_file": "", "source_location": ""}, {"id": "memory_tools_storememorytool", "label": "StoreMemoryTool", "file_type": "code", "source_file": "/mnt/workflows/workflows/apps/backend/app/tools/memory_tools.py", "source_location": "L29"}, {"id": "basetool", "label": "BaseTool", "file_type": "code", "source_file": "", "source_location": ""}, {"id": "memory_tools_name", "label": "name()", "file_type": "code", "source_file": "/mnt/workflows/workflows/apps/backend/app/tools/memory_tools.py", "source_location": "L38"}, {"id": "memory_tools_description", "label": "description()", "file_type": "code", "source_file": "/mnt/workflows/workflows/apps/backend/app/tools/memory_tools.py", "source_location": "L42"}, {"id": "memory_tools_input_schema", "label": "input_schema()", "file_type": "code", "source_file": "/mnt/workflows/workflows/apps/backend/app/tools/memory_tools.py", "source_location": "L50"}, {"id": "memory_tools_tags", "label": "tags()", "file_type": "code", "source_file": "/mnt/workflows/workflows/apps/backend/app/tools/memory_tools.py", "source_location": "L54"}, {"id": "memory_tools_storememorytool_execute", "label": ".execute()", "file_type": "code", "source_file": "/mnt/workflows/workflows/apps/backend/app/tools/memory_tools.py", "source_location": "L57"}, {"id": "memory_tools_recallmemoryinput", "label": "RecallMemoryInput", "file_type": "code", "source_file": "/mnt/workflows/workflows/apps/backend/app/tools/memory_tools.py", "source_location": "L97"}, {"id": "memory_tools_recallmemorytool", "label": "RecallMemoryTool", "file_type": "code", "source_file": "/mnt/workflows/workflows/apps/backend/app/tools/memory_tools.py", "source_location": "L111"}, {"id": "memory_tools_recallmemorytool_execute", "label": ".execute()", "file_type": "code", "source_file": "/mnt/workflows/workflows/apps/backend/app/tools/memory_tools.py", "source_location": "L139"}, {"id": "memory_tools_rationale_1", "label": "Memory Tools  Wraps agent_memory_service.py + agent_vector_store.py for per-agen", "file_type": "rationale", "source_file": "/mnt/workflows/workflows/apps/backend/app/tools/memory_tools.py", "source_location": "L1"}, {"id": "memory_tools_rationale_16", "label": "Input schema for store_memory tool", "file_type": "rationale", "source_file": "/mnt/workflows/workflows/apps/backend/app/tools/memory_tools.py", "source_location": "L16"}, {"id": "memory_tools_rationale_30", "label": "Store a memory for an agent.      Wraps AgentMemoryService.store_memory() to per", "file_type": "rationale", "source_file": "/mnt/workflows/workflows/apps/backend/app/tools/memory_tools.py", "source_location": "L30"}, {"id": "memory_tools_rationale_58", "label": "Store memory using AgentMemoryService", "file_type": "rationale", "source_file": "/mnt/workflows/workflows/apps/backend/app/tools/memory_tools.py", "source_location": "L58"}, {"id": "memory_tools_rationale_98", "label": "Input schema for recall_memory tool", "file_type": "rationale", "source_file": "/mnt/workflows/workflows/apps/backend/app/tools/memory_tools.py", "source_location": "L98"}, {"id": "memory_tools_rationale_112", "label": "Recall memories for an agent.      Wraps AgentMemoryService.search() and get_con", "file_type": "rationale", "source_file": "/mnt/workflows/workflows/apps/backend/app/tools/memory_tools.py", "source_location": "L112"}, {"id": "memory_tools_rationale_140", "label": "Recall memories using AgentMemoryService", "file_type": "rationale", "source_file": "/mnt/workflows/workflows/apps/backend/app/tools/memory_tools.py", "source_location": "L140"}], "edges": [{"source": "memory_tools", "target": "typing", "relation": "imports_from", "confidence": "EXTRACTED", "source_file": "/mnt/workflows/workflows/apps/backend/app/tools/memory_tools.py", "source_location": "L8", "weight": 1.0}, {"source": "memory_tools", "target": "pydantic", "relation": "imports_from", "confidence": "EXTRACTED", "source_file": "/mnt/workflows/workflows/apps/backend/app/tools/memory_tools.py", "source_location": "L10", "weight": 1.0}, {"source": "memory_tools", "target": "base", "relation": "imports_from", "confidence": "EXTRACTED", "source_file": "/mnt/workflows/workflows/apps/backend/app/tools/memory_tools.py", "source_location": "L12", "weight": 1.0}, {"source": "memory_tools", "target": "memory_tools_storememoryinput", "relation": "contains", "confidence": "EXTRACTED", "source_file": "/mnt/workflows/workflows/apps/backend/app/tools/memory_tools.py", "source_location": "L15", "weight": 1.0}, {"source": "memory_tools_storememoryinput", "target": "toolinput", "relation": "inherits", "confidence": "EXTRACTED", "source_file": "/mnt/workflows/workflows/apps/backend/app/tools/memory_tools.py", "source_location": "L15", "weight": 1.0}, {"source": "memory_tools", "target": "memory_tools_storememorytool", "relation": "contains", "confidence": "EXTRACTED", "source_file": "/mnt/workflows/workflows/apps/backend/app/tools/memory_tools.py", "source_location": "L29", "weight": 1.0}, {"source": "memory_tools_storememorytool", "target": "basetool", "relation": "inherits", "confidence": "EXTRACTED", "source_file": "/mnt/workflows/workflows/apps/backend/app/tools/memory_tools.py", "source_location": "L29", "weight": 1.0}, {"source": "memory_tools", "target": "memory_tools_name", "relation": "contains", "confidence": "EXTRACTED", "source_file": "/mnt/workflows/workflows/apps/backend/app/tools/memory_tools.py", "source_location": "L38", "weight": 1.0}, {"source": "memory_tools", "target": "memory_tools_description", "relation": "contains", "confidence": "EXTRACTED", "source_file": "/mnt/workflows/workflows/apps/backend/app/tools/memory_tools.py", "source_location": "L42", "weight": 1.0}, {"source": "memory_tools", "target": "memory_tools_input_schema", "relation": "contains", "confidence": "EXTRACTED", "source_file": "/mnt/workflows/workflows/apps/backend/app/tools/memory_tools.py", "source_location": "L50", "weight": 1.0}, {"source": "memory_tools", "target": "memory_tools_tags", "relation": "contains", "confidence": "EXTRACTED", "source_file": "/mnt/workflows/workflows/apps/backend/app/tools/memory_tools.py", "source_location": "L54", "weight": 1.0}, {"source": "memory_tools_storememorytool", "target": "memory_tools_storememorytool_execute", "relation": "method", "confidence": "EXTRACTED", "source_file": "/mnt/workflows/workflows/apps/backend/app/tools/memory_tools.py", "source_location": "L57", "weight": 1.0}, {"source": "memory_tools", "target": "memory_tools_recallmemoryinput", "relation": "contains", "confidence": "EXTRACTED", "source_file": "/mnt/workflows/workflows/apps/backend/app/tools/memory_tools.py", "source_location": "L97", "weight": 1.0}, {"source": "memory_tools_recallmemoryinput", "target": "toolinput", "relation": "inherits", "confidence": "EXTRACTED", "source_file": "/mnt/workflows/workflows/apps/backend/app/tools/memory_tools.py", "source_location": "L97", "weight": 1.0}, {"source": "memory_tools", "target": "memory_tools_recallmemorytool", "relation": "contains", "confidence": "EXTRACTED", "source_file": "/mnt/workflows/workflows/apps/backend/app/tools/memory_tools.py", "source_location": "L111", "weight": 1.0}, {"source": "memory_tools_recallmemorytool", "target": "basetool", "relation": "inherits", "confidence": "EXTRACTED", "source_file": "/mnt/workflows/workflows/apps/backend/app/tools/memory_tools.py", "source_location": "L111", "weight": 1.0}, {"source": "memory_tools", "target": "memory_tools_name", "relation": "contains", "confidence": "EXTRACTED", "source_file": "/mnt/workflows/workflows/apps/backend/app/tools/memory_tools.py", "source_location": "L120", "weight": 1.0}, {"source": "memory_tools", "target": "memory_tools_description", "relation": "contains", "confidence": "EXTRACTED", "source_file": "/mnt/workflows/workflows/apps/backend/app/tools/memory_tools.py", "source_location": "L124", "weight": 1.0}, {"source": "memory_tools", "target": "memory_tools_input_schema", "relation": "contains", "confidence": "EXTRACTED", "source_file": "/mnt/workflows/workflows/apps/backend/app/tools/memory_tools.py", "source_location": "L132", "weight": 1.0}, {"source": "memory_tools", "target": "memory_tools_tags", "relation": "contains", "confidence": "EXTRACTED", "source_file": "/mnt/workflows/workflows/apps/backend/app/tools/memory_tools.py", "source_location": "L136", "weight": 1.0}, {"source": "memory_tools_recallmemorytool", "target": "memory_tools_recallmemorytool_execute", "relation": "method", "confidence": "EXTRACTED", "source_file": "/mnt/workflows/workflows/apps/backend/app/tools/memory_tools.py", "source_location": "L139", "weight": 1.0}, {"source": "memory_tools_rationale_1", "target": "memory_tools", "relation": "rationale_for", "confidence": "EXTRACTED", "source_file": "/mnt/workflows/workflows/apps/backend/app/tools/memory_tools.py", "source_location": "L1", "weight": 1.0}, {"source": "memory_tools_rationale_16", "target": "memory_tools_storememoryinput", "relation": "rationale_for", "confidence": "EXTRACTED", "source_file": "/mnt/workflows/workflows/apps/backend/app/tools/memory_tools.py", "source_location": "L16", "weight": 1.0}, {"source": "memory_tools_rationale_30", "target": "memory_tools_storememorytool", "relation": "rationale_for", "confidence": "EXTRACTED", "source_file": "/mnt/workflows/workflows/apps/backend/app/tools/memory_tools.py", "source_location": "L30", "weight": 1.0}, {"source": "memory_tools_rationale_58", "target": "memory_tools_storememorytool_execute", "relation": "rationale_for", "confidence": "EXTRACTED", "source_file": "/mnt/workflows/workflows/apps/backend/app/tools/memory_tools.py", "source_location": "L58", "weight": 1.0}, {"source": "memory_tools_rationale_98", "target": "memory_tools_recallmemoryinput", "relation": "rationale_for", "confidence": "EXTRACTED", "source_file": "/mnt/workflows/workflows/apps/backend/app/tools/memory_tools.py", "source_location": "L98", "weight": 1.0}, {"source": "memory_tools_rationale_112", "target": "memory_tools_recallmemorytool", "relation": "rationale_for", "confidence": "EXTRACTED", "source_file": "/mnt/workflows/workflows/apps/backend/app/tools/memory_tools.py", "source_location": "L112", "weight": 1.0}, {"source": "memory_tools_rationale_140", "target": "memory_tools_recallmemorytool_execute", "relation": "rationale_for", "confidence": "EXTRACTED", "source_file": "/mnt/workflows/workflows/apps/backend/app/tools/memory_tools.py", "source_location": "L140", "weight": 1.0}]}