{"nodes": [{"id": "memory", "label": "memory.py", "file_type": "code", "source_file": "/mnt/workflows/workflows/apps/backend/app/api/v1/memory.py", "source_location": "L1"}, {"id": "memory_list_memories", "label": "list_memories()", "file_type": "code", "source_file": "/mnt/workflows/workflows/apps/backend/app/api/v1/memory.py", "source_location": "L8"}, {"id": "memory_get_memory", "label": "get_memory()", "file_type": "code", "source_file": "/mnt/workflows/workflows/apps/backend/app/api/v1/memory.py", "source_location": "L16"}, {"id": "memory_search_memories", "label": "search_memories()", "file_type": "code", "source_file": "/mnt/workflows/workflows/apps/backend/app/api/v1/memory.py", "source_location": "L33"}, {"id": "memory_extract_memories", "label": "extract_memories()", "file_type": "code", "source_file": "/mnt/workflows/workflows/apps/backend/app/api/v1/memory.py", "source_location": "L38"}, {"id": "memory_list_sessions", "label": "list_sessions()", "file_type": "code", "source_file": "/mnt/workflows/workflows/apps/backend/app/api/v1/memory.py", "source_location": "L43"}, {"id": "memory_get_session", "label": "get_session()", "file_type": "code", "source_file": "/mnt/workflows/workflows/apps/backend/app/api/v1/memory.py", "source_location": "L48"}], "edges": [{"source": "memory", "target": "fastapi", "relation": "imports_from", "confidence": "EXTRACTED", "source_file": "/mnt/workflows/workflows/apps/backend/app/api/v1/memory.py", "source_location": "L1", "weight": 1.0}, {"source": "memory", "target": "memory_list_memories", "relation": "contains", "confidence": "EXTRACTED", "source_file": "/mnt/workflows/workflows/apps/backend/app/api/v1/memory.py", "source_location": "L8", "weight": 1.0}, {"source": "memory", "target": "memory_get_memory", "relation": "contains", "confidence": "EXTRACTED", "source_file": "/mnt/workflows/workflows/apps/backend/app/api/v1/memory.py", "source_location": "L16", "weight": 1.0}, {"source": "memory", "target": "memory_search_memories", "relation": "contains", "confidence": "EXTRACTED", "source_file": "/mnt/workflows/workflows/apps/backend/app/api/v1/memory.py", "source_location": "L33", "weight": 1.0}, {"source": "memory", "target": "memory_extract_memories", "relation": "contains", "confidence": "EXTRACTED", "source_file": "/mnt/workflows/workflows/apps/backend/app/api/v1/memory.py", "source_location": "L38", "weight": 1.0}, {"source": "memory", "target": "memory_list_sessions", "relation": "contains", "confidence": "EXTRACTED", "source_file": "/mnt/workflows/workflows/apps/backend/app/api/v1/memory.py", "source_location": "L43", "weight": 1.0}, {"source": "memory", "target": "memory_get_session", "relation": "contains", "confidence": "EXTRACTED", "source_file": "/mnt/workflows/workflows/apps/backend/app/api/v1/memory.py", "source_location": "L48", "weight": 1.0}]}